odoo/addons/l10n_pt_future_account/__init__.py
odoo/addons/l10n_pt_future_account/__manifest__.py
odoo/addons/l10n_pt_future_account/i18n/l10n_pt_future_account.pot
odoo/addons/l10n_pt_future_account/models/__init__.py
odoo/addons/l10n_pt_future_account/models/account_move.py
odoo/addons/l10n_pt_future_account/static/description/icon.png
odoo/addons/l10n_pt_future_account/views/report_invoice.xml
odoo_addon_l10n_pt_future_account-18.0.1.0.0.2.dist-info/METADATA
odoo_addon_l10n_pt_future_account-18.0.1.0.0.2.dist-info/WHEEL
odoo_addon_l10n_pt_future_account-18.0.1.0.0.2.dist-info/top_level.txt
odoo_addon_l10n_pt_future_account-18.0.1.0.0.2.dist-info/RECORD
